hmd_lib_manifest/__init__.py
hmd_lib_manifest/hmd_lib_manifest.py
hmd_lib_manifest/types.py
hmd_lib_manifest-0.1.3.dist-info/METADATA
hmd_lib_manifest-0.1.3.dist-info/WHEEL
hmd_lib_manifest-0.1.3.dist-info/top_level.txt
hmd_lib_manifest-0.1.3.dist-info/RECORD
