Metadata-Version: 2.1
Name: hmd-lib-manifest
Version: 0.1.3
Summary: Library for interacting with NeuronSphere project manifest files
Home-page: UNKNOWN
Author: Alex Burgoon
Author-email: alex.burgoon@hmdlabs.io
License: unlicensed
Platform: UNKNOWN
